variations/__init__.py
variations/conf.py
variations/scaler.py
variations/typing.py
variations/utils.py
variations/variation.py
variations/processors/__init__.py
variations/processors/base.py
variations/processors/crop.py
variations/processors/filters.py
variations/processors/overlay.py
variations/processors/resize.py
variations-0.3.3.dist-info/LICENSE
variations-0.3.3.dist-info/METADATA
variations-0.3.3.dist-info/WHEEL
variations-0.3.3.dist-info/top_level.txt
variations-0.3.3.dist-info/RECORD
