Metadata-Version: 2.1
Name: variations
Version: 0.3.3
Summary: A simple interface that allows processing of images.
Home-page: https://github.com/dldevinc/variations
Author: Mihail Mishakin
Author-email: x896321475@gmail.com
Maintainer: Mihail Mishakin
Maintainer-email: x896321475@gmail.com
License: BSD license
Platform: OS Independent
Classifier: Intended Audience :: Developers
Classifier: Development Status :: 4 - Beta
Classifier: License :: OSI Approved :: BSD License
Classifier: Operating System :: OS Independent
Classifier: Programming Language :: Python
Classifier: Programming Language :: Python :: 3
Classifier: Programming Language :: Python :: 3 :: Only
Classifier: Programming Language :: Python :: 3.7
Classifier: Programming Language :: Python :: 3.8
Classifier: Programming Language :: Python :: 3.9
Classifier: Programming Language :: Python :: 3.10
Classifier: Programming Language :: Python :: 3.11
Classifier: Topic :: Software Development :: Libraries :: Python Modules
Requires-Python: >=3.7
License-File: LICENSE
Requires-Dist: Pillow (>=5.2.0)
Requires-Dist: pilkit (>=1.1.6)
Provides-Extra: facedetection
Requires-Dist: face-recognition ; extra == 'facedetection'
Provides-Extra: full
Requires-Dist: face-recognition ; extra == 'full'
Requires-Dist: pillow-stackblur ; extra == 'full'
Provides-Extra: stackblur
Requires-Dist: pillow-stackblur ; extra == 'stackblur'
